{"batchcomplete": "", "continue": {"apcontinue": "肉盾", "continue": "-||"}, "limits": {"allpages": 500}, "query": {"allpages": [{"pageid": 508543, "ns": 0, "title": "翼(偶像大师)"}, {"pageid": 483372, "ns": 0, "title": "翼(妹妹公主)"}, {"pageid": 498571, "ns": 0, "title": "翼(斗破苍穹)"}, {"pageid": 574871, "ns": 0, "title": "翼(杏之助)"}, {"pageid": 465094, "ns": 0, "title": "翼(虚拟偶像)"}, {"pageid": 325904, "ns": 0, "title": "翼(辉夜大小姐想让我告白)"}, {"pageid": 618150, "ns": 0, "title": "翼(魔法少女奈叶)"}, {"pageid": 370492, "ns": 0, "title": "翼-RESERVoir CHRoNiCLE-"}, {"pageid": 602450, "ns": 0, "title": "翼Gravity"}, {"pageid": 586358, "ns": 0, "title": "翼 La Liberte"}, {"pageid": 586359, "ns": 0, "title": "翼 La Liberté"}, {"pageid": 230635, "ns": 0, "title": "翼 ～memories of maple story～"}, {"pageid": 325886, "ns": 0, "title": "翼·年代记"}, {"pageid": 609117, "ns": 0, "title": "翼の子-Flying Child-"}, {"pageid": 512816, "ns": 0, "title": "翼の歌"}, {"pageid": 614429, "ns": 0, "title": "翼の詩"}, {"pageid": 265944, "ns": 0, "title": "翼はないけど"}, {"pageid": 492003, "ns": 0, "title": "翼をあげたい"}, {"pageid": 213915, "ns": 0, "title": "翼をください"}, {"pageid": 639711, "ns": 0, "title": "翼を持つ者たち"}, {"pageid": 497011, "ns": 0, "title": "翼モラトリアム"}, {"pageid": 511522, "ns": 0, "title": "翼与伴星"}, {"pageid": 470318, "ns": 0, "title": "翼之光"}, {"pageid": 567421, "ns": 0, "title": "翼之国"}, {"pageid": 567671, "ns": 0, "title": "翼之基地区域"}, {"pageid": 609116, "ns": 0, "title": "翼之子-Flying Child-"}, {"pageid": 490912, "ns": 0, "title": "翼之要塞区域"}, {"pageid": 550176, "ns": 0, "title": "翼之诗"}, {"pageid": 291638, "ns": 0, "title": "翼之魔妖-天狗"}, {"pageid": 518770, "ns": 0, "title": "翼人"}, {"pageid": 536381, "ns": 0, "title": "翼侯大人"}, {"pageid": 2276, "ns": 0, "title": "翼号列车娘"}, {"pageid": 325888, "ns": 0, "title": "翼年代记"}, {"pageid": 637702, "ns": 0, "title": "翼彼心苗"}, {"pageid": 378560, "ns": 0, "title": "翼手龙"}, {"pageid": 507616, "ns": 0, "title": "翼田冬生"}, {"pageid": 102891, "ns": 0, "title": "翼神传说"}, {"pageid": 306670, "ns": 0, "title": "翼神龙"}, {"pageid": 544936, "ns": 0, "title": "翼莉雅"}, {"pageid": 544939, "ns": 0, "title": "翼莉雅Eliya"}, {"pageid": 289316, "ns": 0, "title": "翼蛋精灵"}, {"pageid": 378558, "ns": 0, "title": "翼龙"}, {"pageid": 283192, "ns": 0, "title": "翼龙战士"}, {"pageid": 629006, "ns": 0, "title": "翼龙种"}, {"pageid": 539922, "ns": 0, "title": "耀"}, {"pageid": 509894, "ns": 0, "title": "耀かし"}, {"pageid": 499702, "ns": 0, "title": "耀世微光"}, {"pageid": 200557, "ns": 0, "title": "耀于至远之枪"}, {"pageid": 557975, "ns": 0, "title": "耀光"}, {"pageid": 617871, "ns": 0, "title": "耀嘉音"}, {"pageid": 169569, "ns": 0, "title": "耀夜姬"}, {"pageid": 635086, "ns": 0, "title": "耀斑"}, {"pageid": 635012, "ns": 0, "title": "耀斑 Flares of the Blazing Sun"}, {"pageid": 346018, "ns": 0, "title": "耀日"}, {"pageid": 633568, "ns": 0, "title": "耀眼的夜晚，与彗星"}, {"pageid": 441053, "ns": 0, "title": "耀眼的少年"}, {"pageid": 436124, "ns": 0, "title": "耀眼的爱"}, {"pageid": 529317, "ns": 0, "title": "耀眼的纯白之乡"}, {"pageid": 552356, "ns": 0, "title": "耀眼飘落的樱花"}, {"pageid": 493413, "ns": 0, "title": "耀西"}, {"pageid": 325486, "ns": 0, "title": "耀西的手工世界"}, {"pageid": 482976, "ns": 0, "title": "耀西系列"}, {"pageid": 484182, "ns": 0, "title": "耀骑士临光"}, {"pageid": 293482, "ns": 0, "title": "老E"}, {"pageid": 382130, "ns": 0, "title": "老oo了"}, {"pageid": 312050, "ns": 0, "title": "老七和阿云"}, {"pageid": 561965, "ns": 0, "title": "老东西，你的替身最没用了"}, {"pageid": 44151, "ns": 0, "title": "老中医"}, {"pageid": 470298, "ns": 0, "title": "老中医(画江湖)"}, {"pageid": 484820, "ns": 0, "title": "老二次元"}, {"pageid": 275326, "ns": 0, "title": "老亚当酒吧"}, {"pageid": 366912, "ns": 0, "title": "老人"}, {"pageid": 563589, "ns": 0, "title": "老人と海"}, {"pageid": 473626, "ns": 0, "title": "老人与海"}, {"pageid": 230671, "ns": 0, "title": "老人之旅"}, {"pageid": 547503, "ns": 0, "title": "老人星"}, {"pageid": 558175, "ns": 0, "title": "老人街"}, {"pageid": 80721, "ns": 0, "title": "老仓育"}, {"pageid": 542760, "ns": 0, "title": "老八"}, {"pageid": 545225, "ns": 0, "title": "老六"}, {"pageid": 338470, "ns": 0, "title": "老兵回忆录"}, {"pageid": 435668, "ns": 0, "title": "老冰棍"}, {"pageid": 525923, "ns": 0, "title": "老凉头就是涯芝"}, {"pageid": 257158, "ns": 0, "title": "老化的诅咒"}, {"pageid": 460355, "ns": 0, "title": "老北京学粤语"}, {"pageid": 435011, "ns": 0, "title": "老千层饼了"}, {"pageid": 248781, "ns": 0, "title": "老千御法度"}, {"pageid": 486307, "ns": 0, "title": "老友的女儿逼上门"}, {"pageid": 71752, "ns": 0, "title": "老司机"}, {"pageid": 460857, "ns": 0, "title": "老君"}, {"pageid": 414974, "ns": 0, "title": "老君(罗小黑战记)"}, {"pageid": 238653, "ns": 0, "title": "老哥稳"}, {"pageid": 569184, "ns": 0, "title": "老大什么的不干了啦！"}, {"pageid": 255507, "ns": 0, "title": "老大去哪儿"}, {"pageid": 473949, "ns": 0, "title": "老大哥在注视着你"}, {"pageid": 473951, "ns": 0, "title": "老大哥在看着你"}, {"pageid": 473950, "ns": 0, "title": "老大哥正在看着你"}, {"pageid": 623618, "ns": 0, "title": "老天师"}, {"pageid": 591198, "ns": 0, "title": "老天师(明日方舟)"}, {"pageid": 635187, "ns": 0, "title": "老太婆"}, {"pageid": 202469, "ns": 0, "title": "老太婆(CookieClicker)"}, {"pageid": 156315, "ns": 0, "title": "老夫子"}, {"pageid": 156312, "ns": 0, "title": "老夫子(作品)"}, {"pageid": 87499, "ns": 0, "title": "老夫子(王泽)"}, {"pageid": 439099, "ns": 0, "title": "老夫老妻重返青春"}, {"pageid": 32863, "ns": 0, "title": "老头滚动条"}, {"pageid": 482160, "ns": 0, "title": "老头环"}, {"pageid": 207185, "ns": 0, "title": "老奶奶(Dishonored)"}, {"pageid": 167558, "ns": 0, "title": "老好人"}, {"pageid": 531651, "ns": 0, "title": "老婆"}, {"pageid": 348722, "ns": 0, "title": "老婆婆少女日向妹妹"}, {"pageid": 296070, "ns": 0, "title": "老子再去三八线上浪一回"}, {"pageid": 272588, "ns": 0, "title": "老子是魔法少女"}, {"pageid": 71641, "ns": 0, "title": "老子有oo你怕不怕"}, {"pageid": 412954, "ns": 0, "title": "老孙"}, {"pageid": 549642, "ns": 0, "title": "老孟"}, {"pageid": 424092, "ns": 0, "title": "老宅"}, {"pageid": 504434, "ns": 0, "title": "老实人"}, {"pageid": 642497, "ns": 0, "title": "老实人孤立你"}, {"pageid": 365520, "ns": 0, "title": "老实人，孤立他"}, {"pageid": 258054, "ns": 0, "title": "老实人，孤立你"}, {"pageid": 295762, "ns": 0, "title": "老实点每次扫黄都有你"}, {"pageid": 295770, "ns": 0, "title": "老实点，每次扫黄都有你"}, {"pageid": 459866, "ns": 0, "title": "老山龙"}, {"pageid": 441717, "ns": 0, "title": "老崔"}, {"pageid": 95388, "ns": 0, "title": "老师"}, {"pageid": 339754, "ns": 0, "title": "老师(哆啦A梦)"}, {"pageid": 491404, "ns": 0, "title": "老师(宝可梦)"}, {"pageid": 237479, "ns": 0, "title": "老师(战斗女子高校)"}, {"pageid": 429484, "ns": 0, "title": "老师(电击小子)"}, {"pageid": 95346, "ns": 0, "title": "老师(电器街的漫画店)"}, {"pageid": 182740, "ns": 0, "title": "老师(萌属性)"}, {"pageid": 529334, "ns": 0, "title": "老师(蔚蓝档案)"}, {"pageid": 327626, "ns": 0, "title": "老师、我喜欢你。"}, {"pageid": 628581, "ns": 0, "title": "老师、那个啊"}, {"pageid": 69504, "ns": 0, "title": "老师与二宫同学"}, {"pageid": 374276, "ns": 0, "title": "老师听我说"}, {"pageid": 290258, "ns": 0, "title": "老师温柔的杀人方法"}, {"pageid": 360462, "ns": 0, "title": "老师的新娘是16岁的合法萝莉？"}, {"pageid": 634016, "ns": 0, "title": "老师老师"}, {"pageid": 506210, "ns": 0, "title": "老师老师(IA)"}, {"pageid": 633997, "ns": 0, "title": "老师老师(pinata)"}, {"pageid": 374270, "ns": 0, "title": "老师那个呐"}, {"pageid": 374274, "ns": 0, "title": "老师那个呢"}, {"pageid": 324888, "ns": 0, "title": "老师！请让我休息！"}, {"pageid": 278866, "ns": 0, "title": "老师，我喜欢你。"}, {"pageid": 616603, "ns": 0, "title": "老师，我想跳舞"}, {"pageid": 628585, "ns": 0, "title": "老师，那个啊"}, {"pageid": 363140, "ns": 0, "title": "老年人看手机"}, {"pageid": 241781, "ns": 0, "title": "老年吸血鬼"}, {"pageid": 590601, "ns": 0, "title": "老府"}, {"pageid": 388578, "ns": 0, "title": "老式滚动条"}, {"pageid": 462940, "ns": 0, "title": "老式重型救援车"}, {"pageid": 547222, "ns": 0, "title": "老後に備えて異世界で8万枚の金貨を貯めます"}, {"pageid": 542119, "ns": 0, "title": "老恶魔王"}, {"pageid": 560512, "ns": 0, "title": "老搭档糕点师"}, {"pageid": 550042, "ns": 0, "title": "老旧的收音机"}, {"pageid": 310050, "ns": 0, "title": "老板"}, {"pageid": 348864, "ns": 0, "title": "老板(JOJO的奇妙冒险)"}, {"pageid": 372094, "ns": 0, "title": "老板(哑舍)"}, {"pageid": 534852, "ns": 0, "title": "老板(宝可梦)"}, {"pageid": 627603, "ns": 0, "title": "老板(白荆回廊)"}, {"pageid": 588534, "ns": 0, "title": "老板亲卫队"}, {"pageid": 309422, "ns": 0, "title": "老板娘"}, {"pageid": 406816, "ns": 0, "title": "老板娘(Mo4)"}, {"pageid": 621668, "ns": 0, "title": "老桂"}, {"pageid": 417426, "ns": 0, "title": "老桥"}, {"pageid": 465690, "ns": 0, "title": "老法师"}, {"pageid": 260658, "ns": 0, "title": "老滚"}, {"pageid": 629442, "ns": 0, "title": "老滚4"}, {"pageid": 474441, "ns": 0, "title": "老滚5"}, {"pageid": 573900, "ns": 0, "title": "老爷爷"}, {"pageid": 207471, "ns": 0, "title": "老爷爷DISCO"}, {"pageid": 285816, "ns": 0, "title": "老爷级海星男孩"}, {"pageid": 212525, "ns": 0, "title": "老爹"}, {"pageid": 212185, "ns": 0, "title": "老爹(成龙历险记)"}, {"pageid": 452585, "ns": 0, "title": "老爹塔可店"}, {"pageid": 443123, "ns": 0, "title": "老爹披萨店"}, {"pageid": 466930, "ns": 0, "title": "老爹披萨店历险记"}, {"pageid": 442094, "ns": 0, "title": "老爹汉堡店"}, {"pageid": 459113, "ns": 0, "title": "老爹煎饼店"}, {"pageid": 439580, "ns": 0, "title": "老爹系列"}, {"pageid": 582772, "ns": 0, "title": "老爹系列/次要角色"}, {"pageid": 439507, "ns": 0, "title": "老爹路易"}, {"pageid": 494903, "ns": 0, "title": "老爹路易的朋友们"}, {"pageid": 451597, "ns": 0, "title": "老爹餐厅系列"}, {"pageid": 439771, "ns": 0, "title": "老爹餐厅系列/老爹饼干圣代店出现的食材"}, {"pageid": 336924, "ns": 0, "title": "老番茄"}, {"pageid": 245271, "ns": 0, "title": "老破车"}, {"pageid": 498260, "ns": 0, "title": "老福"}, {"pageid": 503592, "ns": 0, "title": "老紫"}, {"pageid": 630374, "ns": 0, "title": "老翁龙"}, {"pageid": 434209, "ns": 0, "title": "老者(十二生肖)"}, {"pageid": 436069, "ns": 0, "title": "老色批"}, {"pageid": 220255, "ns": 0, "title": "老虎"}, {"pageid": 442030, "ns": 0, "title": "老虎与兔子"}, {"pageid": 427986, "ns": 0, "title": "老虎吃小孩"}, {"pageid": 173500, "ns": 0, "title": "老虎和兔子"}, {"pageid": 41967, "ns": 0, "title": "老虎子"}, {"pageid": 273830, "ns": 0, "title": "老虎斧战士"}, {"pageid": 122953, "ns": 0, "title": "老虚"}, {"pageid": 331504, "ns": 0, "title": "老街北"}, {"pageid": 642755, "ns": 0, "title": "老谢斯特宁"}, {"pageid": 169448, "ns": 0, "title": "老贼"}, {"pageid": 483485, "ns": 0, "title": "老贼(歌曲)"}, {"pageid": 450758, "ns": 0, "title": "老郑"}, {"pageid": 247905, "ns": 0, "title": "老铁"}, {"pageid": 400576, "ns": 0, "title": "老铁们，我做的对吗"}, {"pageid": 216687, "ns": 0, "title": "老阿訇"}, {"pageid": 597333, "ns": 0, "title": "老鬼"}, {"pageid": 335194, "ns": 0, "title": "老鬼(人中之龙)"}, {"pageid": 500521, "ns": 0, "title": "老鲤"}, {"pageid": 525908, "ns": 0, "title": "老鸭"}, {"pageid": 352140, "ns": 0, "title": "老鹰"}, {"pageid": 473891, "ns": 0, "title": "老鹰之歌"}, {"pageid": 441716, "ns": 0, "title": "老麦"}, {"pageid": 567053, "ns": 0, "title": "老鼠"}, {"pageid": 408242, "ns": 0, "title": "老鼠与饭团"}, {"pageid": 508191, "ns": 0, "title": "老鼠战队鼠连者"}, {"pageid": 471541, "ns": 0, "title": "老鼠死掉了"}, {"pageid": 513898, "ns": 0, "title": "老鼠死掉了new words w/扩声器"}, {"pageid": 57374, "ns": 0, "title": "老鼠火星历险记"}, {"pageid": 607795, "ns": 0, "title": "考えすぎている"}, {"pageid": 606090, "ns": 0, "title": "考上状元就回来娶我吧"}, {"pageid": 210763, "ns": 0, "title": "考列斯·弗尔维吉"}, {"pageid": 210761, "ns": 0, "title": "考列斯·弗尔维吉·千界树"}, {"pageid": 104858, "ns": 0, "title": "考古"}, {"pageid": 346694, "ns": 0, "title": "考古学家"}, {"pageid": 575335, "ns": 0, "title": "考古式科研"}, {"pageid": 428697, "ns": 0, "title": "考哥"}, {"pageid": 316884, "ns": 0, "title": "考哥.jpg"}, {"pageid": 544136, "ns": 0, "title": "考哥.ntr"}, {"pageid": 125772, "ns": 0, "title": "考大学"}, {"pageid": 605581, "ns": 0, "title": "考娜"}, {"pageid": 244827, "ns": 0, "title": "考崎千鸟"}, {"pageid": 495848, "ns": 0, "title": "考德"}, {"pageid": 473793, "ns": 0, "title": "考拉娘"}, {"pageid": 35039, "ns": 0, "title": "考据党"}, {"pageid": 560037, "ns": 0, "title": "考沃斯"}, {"pageid": 80594, "ns": 0, "title": "考现学部"}, {"pageid": 315064, "ns": 0, "title": "考试"}, {"pageid": 345256, "ns": 0, "title": "考试作弊"}, {"pageid": 506008, "ns": 0, "title": "考试周破防"}, {"pageid": 194180, "ns": 0, "title": "考试王"}, {"pageid": 517950, "ns": 0, "title": "考验支援者"}, {"pageid": 221487, "ns": 0, "title": "而且没有人爱你"}, {"pageid": 547885, "ns": 0, "title": "而后我慢慢地呼吸"}, {"pageid": 497348, "ns": 0, "title": "而我必须逆风执火"}, {"pageid": 569430, "ns": 0, "title": "而我飞过十一年春天"}, {"pageid": 172496, "ns": 0, "title": "而是你要享受这个过程"}, {"pageid": 612156, "ns": 0, "title": "耍把戏"}, {"pageid": 113706, "ns": 0, "title": "耍蛇人戈尔娜莎"}, {"pageid": 629047, "ns": 0, "title": "耐o王"}, {"pageid": 522666, "ns": 0, "title": "耐子的日常"}, {"pageid": 322010, "ns": 0, "title": "耐心(Undertale)"}, {"pageid": 440673, "ns": 0, "title": "耐心蜘蛛"}, {"pageid": 244803, "ns": 0, "title": "耐撕"}, {"pageid": 116318, "ns": 0, "title": "耐耐"}, {"pageid": 334464, "ns": 0, "title": "耐莉"}, {"pageid": 603708, "ns": 0, "title": "耐莉(边狱公司)"}, {"pageid": 334432, "ns": 0, "title": "耐莉·维尔萨拉泽"}, {"pageid": 334436, "ns": 0, "title": "耐莉·薇萨拉兹"}, {"pageid": 56862, "ns": 0, "title": "耐萝"}, {"pageid": 57106, "ns": 0, "title": "耐萝教练姬"}, {"pageid": 171833, "ns": 0, "title": "耐萨里奥"}, {"pageid": 457959, "ns": 0, "title": "耕地机"}, {"pageid": 436883, "ns": 0, "title": "耗子尾汁"}, {"pageid": 437785, "ns": 0, "title": "耗子煨汁"}, {"pageid": 490217, "ns": 0, "title": "耗纸"}, {"pageid": 549261, "ns": 0, "title": "耳のあるロボットの唄"}, {"pageid": 120693, "ns": 0, "title": "耳の中へ"}, {"pageid": 520793, "ns": 0, "title": "耳光"}, {"pageid": 402008, "ns": 0, "title": "耳坠"}, {"pageid": 288870, "ns": 0, "title": "耳天使"}, {"pageid": 199185, "ns": 0, "title": "耳套"}, {"pageid": 338576, "ns": 0, "title": "耳小町"}, {"pageid": 568264, "ns": 0, "title": "耳年齢テスト"}, {"pageid": 256281, "ns": 0, "title": "耳搔"}, {"pageid": 365470, "ns": 0, "title": "耳朵(熊出没)"}, {"pageid": 355526, "ns": 0, "title": "耳朵太郎"}, {"pageid": 116341, "ns": 0, "title": "耳机"}, {"pageid": 293072, "ns": 0, "title": "耳机与蝉时雨"}, {"pageid": 293068, "ns": 0, "title": "耳机与蝉鸣声"}, {"pageid": 81193, "ns": 0, "title": "耳机演绎者"}, {"pageid": 490317, "ns": 0, "title": "耳桥"}, {"pageid": 337312, "ns": 0, "title": "耳状发"}, {"pageid": 168580, "ns": 0, "title": "耳环"}, {"pageid": 221101, "ns": 0, "title": "耳畔晨曦"}, {"pageid": 207557, "ns": 0, "title": "耳罩"}, {"pageid": 624528, "ns": 0, "title": "耳语"}, {"pageid": 620586, "ns": 0, "title": "耳语(在我心底藏了好久)"}, {"pageid": 624526, "ns": 0, "title": "耳语(青柠檬P)"}, {"pageid": 394154, "ns": 0, "title": "耳边头发翘起"}, {"pageid": 262844, "ns": 0, "title": "耳边风风鸟"}, {"pageid": 262846, "ns": 0, "title": "耳边风鸟"}, {"pageid": 277838, "ns": 0, "title": "耳郎响香"}, {"pageid": 458649, "ns": 0, "title": "耳钉"}, {"pageid": 256277, "ns": 0, "title": "耳骚"}, {"pageid": 637419, "ns": 0, "title": "耳鸣蝉"}, {"pageid": 340156, "ns": 0, "title": "耳麦"}, {"pageid": 568257, "ns": 0, "title": "耳龄测试"}, {"pageid": 284722, "ns": 0, "title": "耶利哥"}, {"pageid": 441534, "ns": 0, "title": "耶利哥(底特律:变人)"}, {"pageid": 284950, "ns": 0, "title": "耶利哥(底特律 变人)"}, {"pageid": 284866, "ns": 0, "title": "耶利哥(底特律：化身为人)"}, {"pageid": 455098, "ns": 0, "title": "耶和华"}, {"pageid": 498587, "ns": 0, "title": "耶律塔不烟"}, {"pageid": 558912, "ns": 0, "title": "耶律质舞"}, {"pageid": 493341, "ns": 0, "title": "耶拉"}, {"pageid": 643013, "ns": 0, "title": "耶拉冈德"}, {"pageid": 439154, "ns": 0, "title": "耶斯佩尔·斯文宁森"}, {"pageid": 319614, "ns": 0, "title": "耶格"}, {"pageid": 504080, "ns": 0, "title": "耶格尔派"}, {"pageid": 453100, "ns": 0, "title": "耶梦加得"}, {"pageid": 492739, "ns": 0, "title": "耶梦加得(wotaku)"}, {"pageid": 643853, "ns": 0, "title": "耶梦加得(奥奇传说)"}, {"pageid": 290230, "ns": 0, "title": "耶梦加得(神话生物)"}, {"pageid": 43971, "ns": 0, "title": "耶比迪亚·克里斯托夫"}, {"pageid": 213761, "ns": 0, "title": "耶稣恩友"}, {"pageid": 589789, "ns": 0, "title": "耶稣，世人仰望的喜悦"}, {"pageid": 503270, "ns": 0, "title": "耶绒"}, {"pageid": 627902, "ns": 0, "title": "耶芙娜"}, {"pageid": 349968, "ns": 0, "title": "耶诞节"}, {"pageid": 454377, "ns": 0, "title": "耶路撒冷"}, {"pageid": 386582, "ns": 0, "title": "耶鲁马他哆啦"}, {"pageid": 310602, "ns": 0, "title": "耸肩"}, {"pageid": 641342, "ns": 0, "title": "耻"}, {"pageid": 85859, "ns": 0, "title": "耻力"}, {"pageid": 77579, "ns": 0, "title": "耻度"}, {"pageid": 533223, "ns": 0, "title": "耻烟"}, {"pageid": 582363, "ns": 0, "title": "耻辱系列"}, {"pageid": 629600, "ns": 0, "title": "耽凌"}, {"pageid": 256569, "ns": 0, "title": "耽美"}, {"pageid": 366840, "ns": 0, "title": "耽美党"}, {"pageid": 506129, "ns": 0, "title": "耽美向"}, {"pageid": 283520, "ns": 0, "title": "耽美文"}, {"pageid": 521223, "ns": 0, "title": "耽美游戏"}, {"pageid": 506147, "ns": 0, "title": "耽美番"}, {"pageid": 428340, "ns": 0, "title": "耿六娘"}, {"pageid": 572834, "ns": 0, "title": "耿夏宁"}, {"pageid": 541907, "ns": 0, "title": "耿直"}, {"pageid": 436441, "ns": 0, "title": "耿铭琳"}, {"pageid": 626639, "ns": 0, "title": "耿鬼"}, {"pageid": 172360, "ns": 0, "title": "耿鬼娘"}, {"pageid": 66947, "ns": 0, "title": "聂克丝"}, {"pageid": 544122, "ns": 0, "title": "聂凯"}, {"pageid": 555400, "ns": 0, "title": "聂小倩"}, {"pageid": 519561, "ns": 0, "title": "聂恩"}, {"pageid": 362750, "ns": 0, "title": "聂无悔"}, {"pageid": 537635, "ns": 0, "title": "聂无极"}, {"pageid": 204271, "ns": 0, "title": "聂普姬雅"}, {"pageid": 190995, "ns": 0, "title": "聂普迪努"}, {"pageid": 334224, "ns": 0, "title": "聂曦映"}, {"pageid": 351490, "ns": 0, "title": "聂梓"}, {"pageid": 570632, "ns": 0, "title": "聂洛"}, {"pageid": 589812, "ns": 0, "title": "聂莫琪"}, {"pageid": 589813, "ns": 0, "title": "聂莫黎"}, {"pageid": 374248, "ns": 0, "title": "聂诗柔"}, {"pageid": 197071, "ns": 0, "title": "聂隐娘"}, {"pageid": 512381, "ns": 0, "title": "聆听sonata"}, {"pageid": 444893, "ns": 0, "title": "聆听我的旋律"}, {"pageid": 375990, "ns": 0, "title": "聆听者"}, {"pageid": 266586, "ns": 0, "title": "聆听风声"}, {"pageid": 615933, "ns": 0, "title": "聆柚"}, {"pageid": 593879, "ns": 0, "title": "聆花百合系列"}, {"pageid": 630043, "ns": 0, "title": "聆音"}, {"pageid": 485994, "ns": 0, "title": "聊为信步游"}, {"pageid": 348982, "ns": 0, "title": "聊天鬼才"}, {"pageid": 209531, "ns": 0, "title": "聊播"}, {"pageid": 83571, "ns": 0, "title": "聊斋夜画 梅女"}, {"pageid": 83495, "ns": 0, "title": "聊斋夜画 狐魅"}, {"pageid": 84313, "ns": 0, "title": "聊斋夜画 王二喜"}, {"pageid": 262322, "ns": 0, "title": "聋哑"}, {"pageid": 331146, "ns": 0, "title": "聋的传人"}, {"pageid": 530094, "ns": 0, "title": "职业克制"}, {"pageid": 310776, "ns": 0, "title": "职业树"}, {"pageid": 605472, "ns": 0, "title": "职业玩家"}, {"pageid": 639891, "ns": 0, "title": "职业野球魂A"}, {"pageid": 184528, "ns": 0, "title": "职业雀士"}, {"pageid": 510944, "ns": 0, "title": "职业高尔夫猿"}, {"pageid": 547821, "ns": 0, "title": "职场PUA"}, {"pageid": 386874, "ns": 0, "title": "职场恋情"}, {"pageid": 393068, "ns": 0, "title": "职场欺凌"}, {"pageid": 365860, "ns": 0, "title": "职阶(Fate)"}, {"pageid": 249417, "ns": 0, "title": "职阶卡"}, {"pageid": 221145, "ns": 0, "title": "职阶：主角游戏"}, {"pageid": 357556, "ns": 0, "title": "聒噪鸟"}, {"pageid": 187224, "ns": 0, "title": "联动"}, {"pageid": 560312, "ns": 0, "title": "联动作品"}, {"pageid": 321820, "ns": 0, "title": "联动角色"}, {"pageid": 244649, "ns": 0, "title": "联合军"}, {"pageid": 540180, "ns": 0, "title": "联合军司令伊列娜"}, {"pageid": 395904, "ns": 0, "title": "联合军猎人"}, {"pageid": 601659, "ns": 0, "title": "联合国"}, {"pageid": 52200, "ns": 0, "title": "联合国太空司令部"}, {"pageid": 379636, "ns": 0, "title": "联合国太空同盟"}, {"pageid": 539219, "ns": 0, "title": "联合国太空指挥部"}, {"pageid": 415898, "ns": 0, "title": "联合国航天局"}, {"pageid": 239953, "ns": 0, "title": "联合攻击"}, {"pageid": 463444, "ns": 0, "title": "联合王国"}, {"pageid": 386704, "ns": 0, "title": "联合航天公司"}, {"pageid": 388472, "ns": 0, "title": "联合计划"}, {"pageid": 417078, "ns": 0, "title": "联合麦田"}, {"pageid": 330174, "ns": 0, "title": "联机做梦"}, {"pageid": 582399, "ns": 0, "title": "联盟战棋"}, {"pageid": 446635, "ns": 0, "title": "联盟重型坦克"}, {"pageid": 427668, "ns": 0, "title": "联系之缘 ring"}, {"pageid": 630097, "ns": 0, "title": "联结"}, {"pageid": 231729, "ns": 0, "title": "联络员21O"}, {"pageid": 230837, "ns": 0, "title": "联络员6O"}, {"pageid": 583278, "ns": 0, "title": "联谊"}, {"pageid": 316974, "ns": 0, "title": "联谊会"}, {"pageid": 197890, "ns": 0, "title": "联邦义勇军"}, {"pageid": 571001, "ns": 0, "title": "联邦学生会"}, {"pageid": 99066, "ns": 0, "title": "联邦星舰企业号"}, {"pageid": 582997, "ns": 0, "title": "联邦理事会"}, {"pageid": 49588, "ns": 0, "title": "联邦的MS都是怪物吗"}, {"pageid": 63789, "ns": 0, "title": "联邦调查局"}, {"pageid": 63645, "ns": 0, "title": "联邦调查局娘"}, {"pageid": 261198, "ns": 0, "title": "聖なる日の祈り"}, {"pageid": 635460, "ns": 0, "title": "聖人君子でありたい"}, {"pageid": 507873, "ns": 0, "title": "聖剣なんていらない"}, {"pageid": 429393, "ns": 0, "title": "聖劍同盟"}, {"pageid": 585038, "ns": 0, "title": "聖啟織偶"}, {"pageid": 591039, "ns": 0, "title": "聖夜、愛犬がビデオデッキに詰まる"}, {"pageid": 511060, "ns": 0, "title": "聖女の魔力は万能です"}, {"pageid": 347094, "ns": 0, "title": "聖戦のイベリア"}, {"pageid": 585199, "ns": 0, "title": "聖槌守護者"}, {"pageid": 427141, "ns": 0, "title": "聖槍爆裂ボーイ"}, {"pageid": 437109, "ns": 0, "title": "聖火降魔錄 風花雪月"}, {"pageid": 600658, "ns": 0, "title": "聖祈"}, {"pageid": 167061, "ns": 0, "title": "聖者たち"}, {"pageid": 468232, "ns": 0, "title": "聖者の行進"}, {"pageid": 566071, "ns": 0, "title": "聖者無双 ～サラリーマン、異世界で生き残るために歩む道～"}, {"pageid": 623554, "ns": 0, "title": "聖転使クロスニアハート"}, {"pageid": 526844, "ns": 0, "title": "聖騎士リッカの物語"}, {"pageid": 526843, "ns": 0, "title": "聖騎士リッカの物語 白翼と淫翼の姉妹"}, {"pageid": 625583, "ns": 0, "title": "聘书"}, {"pageid": 455555, "ns": 0, "title": "聚会游戏"}, {"pageid": 561556, "ns": 0, "title": "聚光"}, {"pageid": 629743, "ns": 0, "title": "聚光之刻"}, {"pageid": 476853, "ns": 0, "title": "聚光灯的残火"}, {"pageid": 634054, "ns": 0, "title": "聚变"}, {"pageid": 222879, "ns": 0, "title": "聚散流沙"}, {"pageid": 616955, "ns": 0, "title": "聚猿创团队脑洞中心"}, {"pageid": 269348, "ns": 0, "title": "聚集的祈愿"}, {"pageid": 228103, "ns": 0, "title": "聚集着你想象中梦境的天堂"}, {"pageid": 560251, "ns": 0, "title": "聚集繁星"}, {"pageid": 250897, "ns": 0, "title": "聚集！不可思议研究部"}, {"pageid": 346848, "ns": 0, "title": "聚餐"}, {"pageid": 546185, "ns": 0, "title": "聞いてくれますよね？先輩"}, {"pageid": 625376, "ns": 0, "title": "聞いてよ、ねえ"}, {"pageid": 101803, "ns": 0, "title": "聞き分け厨聖徳太子テスト"}, {"pageid": 101805, "ns": 0, "title": "聞き分け厨聖徳太子テスト＜解答編＞"}, {"pageid": 429720, "ns": 0, "title": "聞こえますか"}, {"pageid": 627419, "ns": 0, "title": "聡明なあのこが、大嫌い"}, {"pageid": 279184, "ns": 0, "title": "聪明曲奇"}, {"pageid": 33417, "ns": 0, "title": "聪明的一休"}, {"pageid": 570991, "ns": 0, "title": "聪明的浣熊"}, {"pageid": 293846, "ns": 0, "title": "聪明的浪漫主义者"}, {"pageid": 555551, "ns": 0, "title": "聪明的狗狗莉莉安塔尔"}, {"pageid": 417564, "ns": 0, "title": "聪明鸟"}, {"pageid": 510985, "ns": 0, "title": "聴こえる？"}, {"pageid": 279700, "ns": 0, "title": "聿怀中学娘"}, {"pageid": 279704, "ns": 0, "title": "聿怀娘"}, {"pageid": 626800, "ns": 0, "title": "聿日笺秋"}, {"pageid": 626798, "ns": 0, "title": "聿日笺秋(单曲)"}, {"pageid": 581855, "ns": 0, "title": "肃圣!! 萝莉神的安魂曲"}, {"pageid": 585594, "ns": 0, "title": "肃圣!!萝莉神的安魂曲"}, {"pageid": 581857, "ns": 0, "title": "肃圣!!萝莉神的安魂曲☆"}, {"pageid": 588715, "ns": 0, "title": "肃声"}, {"pageid": 585330, "ns": 0, "title": "肃声之祈祷者 律"}, {"pageid": 595726, "ns": 0, "title": "肃声的祈祷者 理"}, {"pageid": 275206, "ns": 0, "title": "肃羽"}, {"pageid": 631934, "ns": 0, "title": "肄业"}, {"pageid": 12494, "ns": 0, "title": "肆则楚玪"}, {"pageid": 12493, "ns": 0, "title": "肆则澄佳"}, {"pageid": 635937, "ns": 0, "title": "肆意妄炜的浪漫"}, {"pageid": 320276, "ns": 0, "title": "肆自系列"}, {"pageid": 447712, "ns": 0, "title": "肇和"}, {"pageid": 31613, "ns": 0, "title": "肉"}, {"pageid": 513509, "ns": 0, "title": "肉丸"}, {"pageid": 594880, "ns": 0, "title": "肉体厨"}, {"pageid": 444384, "ns": 0, "title": "肉包怪"}, {"pageid": 301242, "ns": 0, "title": "肉可"}, {"pageid": 555076, "ns": 0, "title": "肉头"}, {"pageid": 611128, "ns": 0, "title": "肉夹馍"}, {"pageid": 304898, "ns": 0, "title": "肉嫁"}, {"pageid": 304954, "ns": 0, "title": "肉嫁高柳家"}, {"pageid": 30615, "ns": 0, "title": "肉山大魔王"}, {"pageid": 497941, "ns": 0, "title": "肉抖抖"}, {"pageid": 208779, "ns": 0, "title": "肉排"}, {"pageid": 560948, "ns": 0, "title": "肉料理的食谱"}, {"pageid": 595946, "ns": 0, "title": "肉斩骨断"}, {"pageid": 3254, "ns": 0, "title": "肉松面包娘"}, {"pageid": 257590, "ns": 0, "title": "肉桂(NEKO WORKs)"}, {"pageid": 502777, "ns": 0, "title": "肉桂卷娘"}, {"pageid": 519364, "ns": 0, "title": "肉桂狗"}, {"pageid": 306928, "ns": 0, "title": "肉樱"}, {"pageid": 25966, "ns": 0, "title": "肉番"}]}}